speedrunpy/__init__.py
speedrunpy/asset.py
speedrunpy/category.py
speedrunpy/client.py
speedrunpy/errors.py
speedrunpy/game.py
speedrunpy/http.py
speedrunpy/level.py
speedrunpy/mixin.py
speedrunpy/name.py
speedrunpy/page.py
speedrunpy/py.typed
speedrunpy/user.py
speedrunpy/utils.py
speedrun.py-21.8.0.dist-info/LICENSE
speedrun.py-21.8.0.dist-info/WHEEL
speedrun.py-21.8.0.dist-info/METADATA
speedrun.py-21.8.0.dist-info/RECORD
