Metadata-Version: 2.1
Name: speedrun.py
Version: 21.8.0
Summary: An asynchronous API wrapper for speedrun.com
License: MIT
Author: null2264
Requires-Python: >=3.8,<4.0
Classifier: License :: OSI Approved :: MIT License
Classifier: Programming Language :: Python :: 3
Classifier: Programming Language :: Python :: 3.8
Classifier: Programming Language :: Python :: 3.9
Requires-Dist: aiohttp (>=3.6.2,<4.0.0)
